aioftp/__init__.py
aioftp/__main__.py
aioftp/client.py
aioftp/common.py
aioftp/errors.py
aioftp/pathio.py
aioftp/py.typed
aioftp/server.py
aioftp-0.26.3.dist-info/METADATA
aioftp-0.26.3.dist-info/WHEEL
aioftp-0.26.3.dist-info/top_level.txt
aioftp-0.26.3.dist-info/RECORD
