Metadata-Version: 2.4
Name: aioftp
Version: 0.26.3
Summary: ftp client/server for asyncio
Author: yieyu, rsichnyi, jw4js, oleksandr-kuzmenko, ndhansen, modelmat, greut, PonyPC, jacobtomlinson, bachya, CrafterKolyan, jkr78, sakosha
Author-email: pohmelie <multisosnooley@gmail.com>, asvetlov <andrew.svetlov@gmail.com>, decaz <decaz89@gmail.com>, janneronkko <janne.ronkko@iki.fi>, thirtyseven <ted@shlashdot.org>, ported-pw <contact@ported.pw>, Olegt0rr <t0rr@mail.ru>, michalc <michal@charemza.name>, ch3pjw <paul@concertdaw.co.uk>, puddly <puddly3@gmail.com>, AMDmi3 <amdmi3@amdmi3.ru>, webknjaz <webknjaz+github/profile@redhat.com>, rcfox <ryan@rcfox.ca>, bellini666 <thiago@bellini.dev>
License:                                  Apache License
Project-URL: Github, https://github.com/aio-libs/aioftp
Project-URL: Documentation, https://aioftp.rtfd.io
Classifier: Programming Language :: Python
Classifier: Programming Language :: Python :: 3
Classifier: Development Status :: 5 - Production/Stable
Classifier: Topic :: Internet :: File Transfer Protocol (FTP)
Requires-Python: >=3.9
Requires-Dist: typing-extensions>=4.13.2; python_version < "3.11"
Provides-Extra: socks
Requires-Dist: siosocks>=0.2.0; extra == "socks"
Provides-Extra: dev
Requires-Dist: async_timeout>=4.0.0; extra == "dev"
Requires-Dist: pytest-asyncio; extra == "dev"
Requires-Dist: pytest-cov; extra == "dev"
Requires-Dist: pytest-mock; extra == "dev"
Requires-Dist: pytest; extra == "dev"
Requires-Dist: siosocks; extra == "dev"
Requires-Dist: trustme; extra == "dev"
Requires-Dist: pre-commit; extra == "dev"
Requires-Dist: ruff; extra == "dev"
Requires-Dist: mypy; extra == "dev"
